tvsongs-0.5.dist-info/RECORD
tvsongs-0.5.dist-info/metadata.json
tvsongs-0.5.dist-info/WHEEL
tvsongs-0.5.dist-info/top_level.txt
tvsongs-0.5.dist-info/DESCRIPTION.rst
tvsongs-0.5.dist-info/METADATA
tvsongs/__init__.py
tvsongs-0.5.data/scripts/tvsongs
