Metadata-Version: 2.0
Name: tvsongs
Version: 0.5
Summary: Find and listen to songs featured in TV shows.
Home-page: https://github.com/zvovov/tvsongs
Author: Chirag Khatri
Author-email: zvovov@gmail.com
License: MIT
Keywords: tvsongs tvsong find search listen tv show series songs music featured
Platform: UNKNOWN
Classifier: Development Status :: 5 - Production/Stable
Classifier: License :: OSI Approved :: MIT License
Classifier: Programming Language :: Python :: 2
Classifier: Programming Language :: Python :: 3
Classifier: Topic :: Multimedia
Classifier: Topic :: Multimedia :: Sound/Audio
Classifier: Topic :: Multimedia :: Sound/Audio :: Analysis
Classifier: Topic :: Text Processing :: General
Requires-Dist: requests
